{
  "version": "2026.3.20-7",
  "platforms": {
    "aarch64-darwin": {
      "url": "https://static.devin.ai/cli/2026.3.20-7/devin-2026.3.20-7-aarch64-apple-darwin.tar.gz",
      "hash": "sha256-IGTY3w8mRNp8p56Nu6mb0J1Yhj3eM87CdCoTFS5v36k="
    },
    "x86_64-darwin": {
      "url": "https://static.devin.ai/cli/2026.3.20-7/devin-2026.3.20-7-x86_64-apple-darwin.tar.gz",
      "hash": "sha256-fjjjdnIWjvLubi806g8XnMxqwkTD8xE0MEhAKMOrqN8="
    },
    "aarch64-linux": {
      "url": "https://static.devin.ai/cli/2026.3.20-7/devin-2026.3.20-7-aarch64-unknown-linux.tar.gz",
      "hash": "sha256-MgWg4UU9OoNMbcjE5S8jq9YqG4x9LsiHP+rlEDbu2FQ="
    },
    "x86_64-linux": {
      "url": "https://static.devin.ai/cli/2026.3.20-7/devin-2026.3.20-7-x86_64-unknown-linux.tar.gz",
      "hash": "sha256-a/Fqf28O52g/mbL9/y1/12dkOFx6bTLOgDhIWti0zqM="
    }
  }
}
